printinglog/__init__.py
printinglog/printinglog.py
printinglog-0.0.1.dist-info/METADATA
printinglog-0.0.1.dist-info/WHEEL
printinglog-0.0.1.dist-info/licenses/LICENSE
printinglog-0.0.1.dist-info/RECORD
