Metadata-Version: 2.3
Name: printinglog
Version: 0.0.1
Summary: Python logging instead of complicated print
Project-URL: Homepage, https://github.com/danjeltahko/printinglog
Project-URL: Issues, https://github.com/danjeltahko/printinglog/issues
Author-email: Tahko <tahkodev@gmail.com>
License-File: LICENSE
Keywords: log,logger,logging,loguru
Classifier: Intended Audience :: Developers
Classifier: License :: OSI Approved :: MIT License
Classifier: Operating System :: OS Independent
Classifier: Programming Language :: Python :: 3
Classifier: Topic :: System :: Logging
Requires-Python: >=3.9
